<?xml version="1.0" encoding="utf-8" ?> 
<Doc>
	<Public>
		<na1>Arithmetic</na1>
		<index>home</index>
		<history>history</history>
		<la>Language Change</la>
		<chBtn>Chinese-Simplified</chBtn>
		<hkBtn>Chinese-Traditional</hkBtn>
		<enBtn>English</enBtn>
		<titleH3>The number of questions:</titleH3>
		<startBtn>Start</startBtn>
		<stopBtn>End</stopBtn>
		<judgeBtn>True or False</judgeBtn>
		<refreshBtn>Refresh</refreshBtn>
		<rightSp>right:</rightSp>
		<wrongSp>wrong:</wrongSp>
		<na1>Arithmetic</na1>
		<head>Welcome to Arithmetic</head>
		<text1>Here you can not only do exercise, but also record the time. Here you can check the exercise history</text1>
		<text2>Here is Arithmetic</text2>
		<toTop>Back to top</toTop>
	</Public>
</Doc>